[
    {
        "name": "Boracay Yoga",
        "address": "Lanterns Hotel Boracay ANANDA SHALA O491 Boracay Bulabog Road Malay",
        "thumbnail": "./images/explore/relax/boracay-yoga.jpeg",
        "contact": "+63 908 265 1818",
        "email": "info@boracayyoga.org",
        "link": "https://www.boracayyoga.org/",
        "notes": ""
    },
    {
        "name": "Cacao Ceremony",
        "address": "Station 2, White Beach Path",
        "thumbnail": "./images/explore/relax/cacao-ceremony.jpeg",
        "contact": "+639289894709",
        "email": "infinitynature88@gmail.com",
        "link": "https://www.instagram.com/cacao.ceremony.world",
        "notes": "Join us for the Sacred Cacao Ceremony around the world"
    }
]